gts_engine/__init__.py
gts_engine/gts_engine_inference.py
gts_engine/gts_engine_service.py
gts_engine/gts_engine_train.py
gts_engine/bagualu/__init__.py
gts_engine/bagualu/arguments/__init__.py
gts_engine/bagualu/arguments/ie/__init__.py
gts_engine/bagualu/arguments/ie/arguments_std.py
gts_engine/bagualu/arguments/summary/__init__.py
gts_engine/bagualu/arguments/summary/arguments_std.py
gts_engine/bagualu/arguments/text_classification/__init__.py
gts_engine/bagualu/arguments/text_classification/arguments_std.py
gts_engine/bagualu/dataloaders/__init__.py
gts_engine/bagualu/dataloaders/ie/__init__.py
gts_engine/bagualu/dataloaders/ie/data_eval_utils.py
gts_engine/bagualu/dataloaders/ie/data_model.py
gts_engine/bagualu/dataloaders/ie/dataset.py
gts_engine/bagualu/dataloaders/ie/dataset_utils.py
gts_engine/bagualu/dataloaders/ie/item_decoder.py
gts_engine/bagualu/dataloaders/ie/item_encoder.py
gts_engine/bagualu/dataloaders/summary/__init__.py
gts_engine/bagualu/dataloaders/summary/data_module.py
gts_engine/bagualu/dataloaders/summary/dataset.py
gts_engine/bagualu/dataloaders/summary/dataset_utils.py
gts_engine/bagualu/dataloaders/text_classification/__init__.py
gts_engine/bagualu/dataloaders/text_classification/data_module_std.py
gts_engine/bagualu/dataloaders/text_classification/datasets_std.py
gts_engine/bagualu/entrances/__init__.py
gts_engine/bagualu/entrances/ie/__init__.py
gts_engine/bagualu/entrances/ie/gts_engine_interface_std.py
gts_engine/bagualu/entrances/ie/inference_manager_std.py
gts_engine/bagualu/entrances/ie/training_pipeline_std.py
gts_engine/bagualu/entrances/summary/__init__.py
gts_engine/bagualu/entrances/summary/gts_engine_interface_std.py
gts_engine/bagualu/entrances/summary/inference_manager_std.py
gts_engine/bagualu/entrances/summary/training_pipeline_std.py
gts_engine/bagualu/entrances/text_classification/__init__.py
gts_engine/bagualu/entrances/text_classification/gts_engine_interface_std.py
gts_engine-0.1.4.dist-info/LICENSE
gts_engine-0.1.4.dist-info/METADATA
gts_engine-0.1.4.dist-info/WHEEL
gts_engine-0.1.4.dist-info/entry_points.txt
gts_engine-0.1.4.dist-info/top_level.txt
gts_engine-0.1.4.dist-info/RECORD
