Metadata-Version: 2.1
Name: gts-engine
Version: 0.1.4
Summary: git_engine development suite: a powerful NLU training system
Home-page: https://github.com/IDEA-CCNL/GTS-Engine
Author: pankunhao
Author-email: pankunhao@gmail.com
License: Apache 2.0
Platform: any
Classifier: Programming Language :: Python :: 3
Classifier: License :: OSI Approved :: MIT License
Classifier: Operating System :: OS Independent
License-File: LICENSE
Requires-Dist: fastapi (==0.86.0)
Requires-Dist: numpy (==1.22.3)
Requires-Dist: psutil (==5.8.0)
Requires-Dist: pydantic (==1.10.2)
Requires-Dist: pynvml (==11.0.0)
Requires-Dist: pytorch-lightning (==1.7.6)
Requires-Dist: scikit-learn (==1.1.3)
Requires-Dist: setuptools (==58.0.4)
Requires-Dist: starlette (==0.20.4)
Requires-Dist: torch (==1.11.0+cu113)
Requires-Dist: tqdm (==4.62.3)
Requires-Dist: transformers (==4.18.0)
Requires-Dist: uvicorn (==0.19.0)
Requires-Dist: python-multipart (==0.0.5)
Requires-Dist: sentence-transformers (==2.2.2)
Requires-Dist: LAC (==2.1.2)
Requires-Dist: textda (==0.1.0.6)
